PyOmics/__init__.py
PyOmics/constants.py
PyOmics/sequence.py
PyOmics-0.0.1.dev6.dist-info/DESCRIPTION.rst
PyOmics-0.0.1.dev6.dist-info/METADATA
PyOmics-0.0.1.dev6.dist-info/RECORD
PyOmics-0.0.1.dev6.dist-info/WHEEL
PyOmics-0.0.1.dev6.dist-info/metadata.json
PyOmics-0.0.1.dev6.dist-info/top_level.txt
