Metadata-Version: 2.0
Name: PyOmics
Version: 0.0.1.dev6
Summary: A library for dealing with omic-data in the life sciences
Home-page: https://github.com/FloBay/PyOmics.git
Author: Florian P. Bayer
Author-email: f.bayer@tum.de
License: MIT
Keywords: PyOmics bioinformatics omics science data analysis easy
Platform: UNKNOWN
Classifier: Development Status :: 1 - Planning
Classifier: Intended Audience :: Science/Research
Classifier: Intended Audience :: Education
Classifier: License :: OSI Approved :: MIT License
Classifier: Natural Language :: English
Classifier: Programming Language :: Python :: 3
Classifier: Topic :: Scientific/Engineering :: Bio-Informatics
Classifier: Topic :: Software Development :: Libraries :: Python Modules
